<annotation>
  <folder>mimages</folder>
  <filename>Kandariya+Mahadev+Temple+Photo</filename>
  <path>C:\Users\sudkum\OneDrive - Microsoft\data_scrapping\AMALAKA\mimages\Kandariya+Mahadev+Temple+Photo.jpg</path>
  <source>
    <database>Unknown</database>
  </source>
  <size>
    <width>400</width>
    <height>300</height>
    <depth>3</depth>
  </size>
  <segmented>0</segmented>
  <object>
    <name>amalaka</name>
    <pose>Unspecified</pose>
    <truncated>0</truncated>
    <difficult>0</difficult>
    <bndbox>
      <xmin>110</xmin>
      <ymin>12</ymin>
      <xmax>152</xmax>
      <ymax>29</ymax>
    </bndbox>
  </object>
  <object>
    <name>gopuram</name>
    <pose>Unspecified</pose>
    <truncated>0</truncated>
    <difficult>0</difficult>
    <bndbox>
      <xmin>88</xmin>
      <ymin>24</ymin>
      <xmax>170</xmax>
      <ymax>137</ymax>
    </bndbox>
  </object>
  <object>
    <name>mandapa</name>
    <pose>Unspecified</pose>
    <truncated>0</truncated>
    <difficult>0</difficult>
    <bndbox>
      <xmin>209</xmin>
      <ymin>154</ymin>
      <xmax>318</xmax>
      <ymax>185</ymax>
    </bndbox>
  </object>
  <object>
    <name>mandapa</name>
    <pose>Unspecified</pose>
    <truncated>0</truncated>
    <difficult>0</difficult>
    <bndbox>
      <xmin>67</xmin>
      <ymin>162</ymin>
      <xmax>115</xmax>
      <ymax>191</ymax>
    </bndbox>
  </object>
</annotation>
