<annotation>
  <folder>mimages</folder>
  <filename>view-of-nandi-mandapa-virupaksha-temple-pattadakal-temple-complex-g1yb4x</filename>
  <path>C:\Users\sudkum\OneDrive - Microsoft\data_scrapping\MANDAPA\mimages\view-of-nandi-mandapa-virupaksha-temple-pattadakal-temple-complex-g1yb4x.jpg</path>
  <source>
    <database>Unknown</database>
  </source>
  <size>
    <width>400</width>
    <height>300</height>
    <depth>3</depth>
  </size>
  <segmented>0</segmented>
  <object>
    <name>mandapa</name>
    <pose>Unspecified</pose>
    <truncated>0</truncated>
    <difficult>0</difficult>
    <bndbox>
      <xmin>19</xmin>
      <ymin>12</ymin>
      <xmax>371</xmax>
      <ymax>235</ymax>
    </bndbox>
  </object>
</annotation>
