<annotation>
  <folder>mimages</folder>
  <filename>Khajuraho+Lakshmana+temple+exterior.jpg</filename>
  <path>/home/sudkum/tensorflow1/models/research/object_detection/images/train/Khajuraho+Lakshmana+temple+exterior.jpg</path>
  <source>
    <database>Unknown</database>
  </source>
  <size>
    <width>400</width>
    <height>300</height>
    <depth>3</depth>
  </size>
  <segmented>0</segmented>
  <object>
    <name>amalaka</name>
    <pose>Unspecified</pose>
    <truncated>0</truncated>
    <difficult>0</difficult>
    <bndbox>
      <xmin>262</xmin>
      <ymin>33</ymin>
      <xmax>327</xmax>
      <ymax>62</ymax>
    </bndbox>
  </object>
  <object>
    <name>gopuram</name>
    <pose>Unspecified</pose>
    <truncated>0</truncated>
    <difficult>0</difficult>
    <bndbox>
      <xmin>249</xmin>
      <ymin>58</ymin>
      <xmax>354</xmax>
      <ymax>210</ymax>
    </bndbox>
  </object>
  <object>
    <name>mandapa</name>
    <pose>Unspecified</pose>
    <truncated>0</truncated>
    <difficult>0</difficult>
    <bndbox>
      <xmin>180</xmin>
      <ymin>245</ymin>
      <xmax>266</xmax>
      <ymax>295</ymax>
    </bndbox>
  </object>
</annotation>